hcautomation/__init__.py
hcautomation/downloader.py
hcautomation/login_generator.py
hcautomation/post_install_setup.py
hcautomation/priv_key.PEM
hcautomation/pub_key.PEM
hcautomation-0.4.0.dist-info/METADATA
hcautomation-0.4.0.dist-info/WHEEL
hcautomation-0.4.0.dist-info/entry_points.txt
hcautomation-0.4.0.dist-info/top_level.txt
hcautomation-0.4.0.dist-info/RECORD
