Metadata-Version: 2.4
Name: hcautomation
Version: 0.4.0
Summary: A Python package for automating LMG processes
Author-email: Harshal <hsarode04@gmail.com>
License: MIT
Requires-Python: >=3.9
Requires-Dist: setuptools
Requires-Dist: pandas
Requires-Dist: numpy
Requires-Dist: selenium
Requires-Dist: rsa
Requires-Dist: bs4
Requires-Dist: pywin32
